sqlathanor/__init__.py
sqlathanor/__version__.py
sqlathanor/_compat.py
sqlathanor/_serialization_support.py
sqlathanor/attributes.py
sqlathanor/automap.py
sqlathanor/default_deserializers.py
sqlathanor/default_serializers.py
sqlathanor/errors.py
sqlathanor/flask_sqlathanor.py
sqlathanor/schema.py
sqlathanor/utilities.py
sqlathanor/declarative/__init__.py
sqlathanor/declarative/_base_configuration_mixin.py
sqlathanor/declarative/_csv_support.py
sqlathanor/declarative/_dict_support.py
sqlathanor/declarative/_json_support.py
sqlathanor/declarative/_primary_key_mixin.py
sqlathanor/declarative/_yaml_support.py
sqlathanor/declarative/base_model.py
sqlathanor/declarative/declarative_base.py
sqlathanor/declarative/generate_model.py
sqlathanor-0.7.0.dist-info/LICENSE
sqlathanor-0.7.0.dist-info/METADATA
sqlathanor-0.7.0.dist-info/WHEEL
sqlathanor-0.7.0.dist-info/top_level.txt
sqlathanor-0.7.0.dist-info/RECORD
