Metadata-Version: 2.1
Name: sqlathanor
Version: 0.7.0
Summary: Serialization/De-serialization Support for the SQLAlchemy Declarative ORM
Home-page: https://sqlathanor.readthedocs.io/en/latest
Author: Insight Industry Inc.
Author-email: software@insightindustry.com
License: MIT
Project-URL: Documentation, https://sqlathanor.readthedocs.io/en/latest
Project-URL: Say Thanks!, https://saythanks.io/to/sqlathanor
Project-URL: Bug Reports, https://github.com/insightindustry/sqlathanor/issues
Project-URL: Source, https://github.com/insightindustry/sqlathanor/
Keywords: sqlalchemy ORM model extension serialization CSV JSON YAML dict deserialization schema
Platform: UNKNOWN
Classifier: Development Status :: 5 - Production/Stable
Classifier: Environment :: Web Environment
Classifier: Operating System :: OS Independent
Classifier: Intended Audience :: Developers
Classifier: Topic :: Software Development :: Libraries
Classifier: Topic :: Utilities
Classifier: Topic :: Internet :: WWW/HTTP :: Dynamic Content
Classifier: Topic :: Software Development :: Libraries :: Python Modules
Classifier: Topic :: Database :: Front-Ends
Classifier: License :: OSI Approved :: MIT License
Classifier: Programming Language :: Python :: 2
Classifier: Programming Language :: Python :: 2.7
Classifier: Programming Language :: Python :: 3
Classifier: Programming Language :: Python :: 3.4
Classifier: Programming Language :: Python :: 3.5
Classifier: Programming Language :: Python :: 3.6
Classifier: Programming Language :: Python :: 3.7
Classifier: Programming Language :: Python :: 3.8
Requires-Python: >=2.7, !=3.0.*, !=3.1.*, !=3.2.*, !=3.3.*, <4
Requires-Dist: validator-collection (>=1.4.0)
Requires-Dist: simplejson (>=3.0)
Requires-Dist: sqlalchemy (>=0.9) ; python_version < "3.7"
Requires-Dist: PyYAML (>=3.10) ; python_version < "3.7"
Requires-Dist: sqlalchemy (>=0.10) ; python_version > "3.6"
Requires-Dist: PyYAML (>=3.13) ; python_version > "3.6"
Provides-Extra: dev
Requires-Dist: check-manifest ; extra == 'dev'
Requires-Dist: sphinx ; extra == 'dev'
Requires-Dist: sphinx-rtd-theme ; extra == 'dev'
Requires-Dist: sphinx-tabs ; extra == 'dev'
Requires-Dist: readme-renderer ; extra == 'dev'
Requires-Dist: restview ; extra == 'dev'
Requires-Dist: Flask-SQLAlchemy ; extra == 'dev'
Provides-Extra: test
Requires-Dist: coverage ; extra == 'test'
Requires-Dist: pytest ; extra == 'test'
Requires-Dist: pytest-benchmark ; extra == 'test'
Requires-Dist: pytest-cov ; extra == 'test'
Requires-Dist: tox ; extra == 'test'
Requires-Dist: codecov ; extra == 'test'
Requires-Dist: Flask-SQLAlchemy ; extra == 'test'
